custodia-0.6.0-py3.6-nspkg.pth
custodia/__about__.py
custodia/client.py
custodia/compat.py
custodia/forwarder.py
custodia/log.py
custodia/plugin.py
custodia/root.py
custodia/secrets.py
custodia/cli/__init__.py
custodia/cli/__main__.py
custodia/httpd/__init__.py
custodia/httpd/authenticators.py
custodia/httpd/authorizers.py
custodia/httpd/consumer.py
custodia/httpd/server.py
custodia/ipa/__init__.py
custodia/ipa/certrequest.py
custodia/ipa/interface.py
custodia/ipa/vault.py
custodia/message/__init__.py
custodia/message/common.py
custodia/message/formats.py
custodia/message/kem.py
custodia/message/simple.py
custodia/server/__init__.py
custodia/server/__main__.py
custodia/server/args.py
custodia/server/config.py
custodia/store/__init__.py
custodia/store/encgen.py
custodia/store/enclite.py
custodia/store/interface.py
custodia/store/sqlite.py
custodia-0.6.0.dist-info/DESCRIPTION.rst
custodia-0.6.0.dist-info/METADATA
custodia-0.6.0.dist-info/RECORD
custodia-0.6.0.dist-info/WHEEL
custodia-0.6.0.dist-info/entry_points.txt
custodia-0.6.0.dist-info/metadata.json
custodia-0.6.0.dist-info/namespace_packages.txt
custodia-0.6.0.dist-info/top_level.txt
