Metadata-Version: 2.0
Name: custodia
Version: 0.6.0
Summary: A service to manage, retrieve and store secrets.
Home-page: https://github.com/latchset/custodia
Author: Custodia project Contributors
Author-email: simo@redhat.com
License: GPLv3+
Platform: UNKNOWN
Classifier: Programming Language :: Python :: 2.7
Classifier: Programming Language :: Python :: 3.5
Classifier: Programming Language :: Python :: 3.6
Classifier: Intended Audience :: Developers
Classifier: Topic :: Security
Classifier: Topic :: Software Development :: Libraries :: Python Modules
Requires-Python: >=2.7,!=3.0.*,!=3.1.*,!=3.2.*,!=3.3.*,!=3.4.*
Requires-Dist: cryptography
Requires-Dist: jwcrypto
Requires-Dist: six
Requires-Dist: requests
Requires-Dist: configparser; python_version<"3.4"
Requires-Dist: mock; python_version<"3.4"
Provides-Extra: gssapi
Requires-Dist: requests-gssapi; extra == 'gssapi'
Provides-Extra: ipa
Requires-Dist: ipalib (>=4.5.0); extra == 'ipa'
Requires-Dist: ipaclient (>=4.5.0); extra == 'ipa'
Provides-Extra: test
Requires-Dist: coverage; extra == 'test'
Requires-Dist: pytest; extra == 'test'
Provides-Extra: test_docs
Requires-Dist: docutils; extra == 'test_docs'
Requires-Dist: markdown; extra == 'test_docs'
Requires-Dist: sphinx-argparse; extra == 'test_docs'
Requires-Dist: sphinxcontrib-spelling; extra == 'test_docs'
Requires-Dist: ipalib (>=4.5.0); extra == 'test_docs'
Requires-Dist: ipaclient (>=4.5.0); extra == 'test_docs'
Provides-Extra: test_extras
Requires-Dist: coverage; extra == 'test_extras'
Requires-Dist: pytest; extra == 'test_extras'
Requires-Dist: requests-gssapi; extra == 'test_extras'
Requires-Dist: ipalib (>=4.5.0); extra == 'test_extras'
Requires-Dist: ipaclient (>=4.5.0); extra == 'test_extras'
Provides-Extra: test_pep8
Requires-Dist: flake8; extra == 'test_pep8'
Requires-Dist: flake8-import-order; extra == 'test_pep8'
Requires-Dist: pep8-naming; extra == 'test_pep8'
Provides-Extra: test_pylint
Requires-Dist: pylint; extra == 'test_pylint'
Requires-Dist: coverage; extra == 'test_pylint'
Requires-Dist: pytest; extra == 'test_pylint'
Requires-Dist: requests-gssapi; extra == 'test_pylint'
Requires-Dist: ipalib (>=4.5.0); extra == 'test_pylint'
Requires-Dist: ipaclient (>=4.5.0); extra == 'test_pylint'
